nuke/__init__.py
nuke/cli.py
nuke/dirtree.py
nuke/nuke.py
nuke/utils.py
nuke-2.6.2.dist-info/METADATA
nuke-2.6.2.dist-info/WHEEL
nuke-2.6.2.dist-info/entry_points.txt
nuke-2.6.2.dist-info/licenses/LICENSE
nuke-2.6.2.dist-info/RECORD
