Metadata-Version: 2.4
Name: nuke
Version: 2.6.2
Summary: Command line tool for nuking a directory 💥
Project-URL: Homepage, https://github.com/varunagrawal/nuke
Project-URL: Issues, https://github.com/varunagrawal/nuke/issues
Author-email: Varun Agrawal <varagrawal@gmail.com>
License: MIT
License-File: LICENSE
Classifier: Development Status :: 5 - Production/Stable
Classifier: Environment :: Console
Classifier: Intended Audience :: Developers
Classifier: License :: OSI Approved :: MIT License
Classifier: Operating System :: MacOS
Classifier: Operating System :: Microsoft :: Windows
Classifier: Operating System :: POSIX
Classifier: Operating System :: Unix
Classifier: Programming Language :: Python :: 3.10
Classifier: Programming Language :: Python :: 3.11
Classifier: Programming Language :: Python :: 3.12
Classifier: Programming Language :: Python :: 3.13
Classifier: Topic :: Software Development :: Libraries :: Python Modules
Requires-Python: >=3.10
Requires-Dist: click>=6.7
Requires-Dist: crayons>=0.1.2
Requires-Dist: rich>=12.6.0
